LICENSE.txt
hoodat_vertex_components/__init__.py
hoodat_vertex_components/components/__init__.py
hoodat_vertex_components/components/add_py/Dockerfile
hoodat_vertex_components/components/add_py/add.py
hoodat_vertex_components/components/add_py/component.yaml
hoodat_vertex_components/components/bytetrack_from_video/Dockerfile
hoodat_vertex_components/components/bytetrack_from_video/Dockerfile_orig
hoodat_vertex_components/components/bytetrack_from_video/component.py
hoodat_vertex_components/components/bytetrack_from_video/component.yaml
hoodat_vertex_components/components/bytetrack_from_video/friends-Scene-008.mp4
hoodat_vertex_components/components/bytetrack_from_video/poetry.lock
hoodat_vertex_components/components/bytetrack_from_video/pyproject.toml
hoodat_vertex_components/components/bytetrack_from_video/requirements.txt
hoodat_vertex_components/components/bytetrack_from_video/tools/demo_track.py
hoodat_vertex_components/components/bytetrack_from_videos/Dockerfile
hoodat_vertex_components/components/bytetrack_from_videos/component.py
hoodat_vertex_components/components/bytetrack_from_videos/component.yaml
hoodat_vertex_components/components/bytetrack_from_videos/friends-Scene-008.mp4
hoodat_vertex_components/components/bytetrack_from_videos/poetry.lock
hoodat_vertex_components/components/bytetrack_from_videos/pyproject.toml
hoodat_vertex_components/components/bytetrack_from_videos/requirements.txt
hoodat_vertex_components/components/bytetrack_from_videos/tools/demo_track.py
hoodat_vertex_components/components/haar_from_frames/Dockerfile
hoodat_vertex_components/components/haar_from_frames/component.py
hoodat_vertex_components/components/haar_from_frames/component.yaml
hoodat_vertex_components/components/make_cascade_file/Dockerfile
hoodat_vertex_components/components/make_cascade_file/cascades.csv
hoodat_vertex_components/components/make_cascade_file/component.yaml
hoodat_vertex_components/components/make_cascade_file/make_cascade_file.py
hoodat_vertex_components-1.6.6.dist-info/LICENSE.txt
hoodat_vertex_components-1.6.6.dist-info/METADATA
hoodat_vertex_components-1.6.6.dist-info/WHEEL
hoodat_vertex_components-1.6.6.dist-info/RECORD
