Metadata-Version: 2.1
Name: hoodat-vertex-components
Version: 1.6.6
Summary: Re-usable kfp components for hoodat
License: MIT
Author: Eugene Brown
Author-email: efbbrown@gmail.com
Requires-Python: >=3.8,<4.0
Classifier: License :: OSI Approved :: MIT License
Classifier: Programming Language :: Python :: 3
Classifier: Programming Language :: Python :: 3.8
Classifier: Programming Language :: Python :: 3.9
Classifier: Programming Language :: Python :: 3.10
Classifier: Programming Language :: Python :: 3.11
Requires-Dist: google-cloud-aiplatform (>=1.12.1,<2.0.0)
Requires-Dist: kfp (>=1.8.12,<2.0.0)
Requires-Dist: pytz (>=2022.5,<2023.0)
